reggae/__init__.py
reggae/reflect.py
reggae/json_build.py
reggae/rules.py
reggae/build.py
reggae-0.1.dist-info/metadata.json
reggae-0.1.dist-info/RECORD
reggae-0.1.dist-info/top_level.txt
reggae-0.1.dist-info/WHEEL
reggae-0.1.dist-info/DESCRIPTION.rst
reggae-0.1.dist-info/METADATA
