Metadata-Version: 2.0
Name: reggae
Version: 0.1
Summary: Python front-end to the Reggae meta-build system
Home-page: https://github.com/atilaneves/reggae-python
Author: Atila Neves
Author-email: atila.neves@gmail.com
License: BSD
Platform: UNKNOWN
